{
    "tracks": {
        "@attr": {
            "page": "9", 
            "perPage": "200", 
            "total": "23384900", 
            "totalPages": "116925"
        }, 
        "track": [
            {
                "artist": {
                    "mbid": "757ed661-fbad-4e45-b1cd-a6b09f06f54a", 
                    "name": "Yung Lean", 
                    "url": "https://www.last.fm/music/Yung+Lean"
                }, 
                "duration": "0", 
                "image": [
                    {
                        "#text": "https://lastfm-img2.akamaized.net/i/u/34s/da3e6b3b86cc52118267b4f8920a3167.png", 
                        "size": "small"
                    }, 
                    {
                        "#text": "https://lastfm-img2.akamaized.net/i/u/64s/da3e6b3b86cc52118267b4f8920a3167.png", 
                        "size": "medium"
                    }, 
                    {
                        "#text": "https://lastfm-img2.akamaized.net/i/u/174s/da3e6b3b86cc52118267b4f8920a3167.png", 
                        "size": "large"
                    }, 
                    {
                        "#text": "https://lastfm-img2.akamaized.net/i/u/300x300/da3e6b3b86cc52118267b4f8920a3167.png", 
                        "size": "extralarge"
                    }
                ], 
                "listeners": "8291", 
                "mbid": "", 
                "name": "Skimask", 
                "playcount": "29426", 
                "streamable": {
                    "#text": "0", 
                    "fulltrack": "0"
                }, 
                "url": "https://www.last.fm/music/Yung+Lean/_/Skimask"
            }, 
            {
                "artist": {
                    "mbid": "164f0d73-1234-4e2c-8743-d77bf2191051", 
                    "name": "Kanye West", 
                    "url": "https://www.last.fm/music/Kanye+West"
                }, 
                "duration": "360", 
                "image": [
                    {
                        "#text": "https://lastfm-img2.akamaized.net/i/u/34s/7b3a1adc3f99719f75e97d4f4a72e0f5.png", 
                        "size": "small"
                    }, 
                    {
                        "#text": "https://lastfm-img2.akamaized.net/i/u/64s/7b3a1adc3f99719f75e97d4f4a72e0f5.png", 
                        "size": "medium"
                    }, 
                    {
                        "#text": "https://lastfm-img2.akamaized.net/i/u/174s/7b3a1adc3f99719f75e97d4f4a72e0f5.png", 
                        "size": "large"
                    }, 
                    {
                        "#text": "https://lastfm-img2.akamaized.net/i/u/300x300/7b3a1adc3f99719f75e97d4f4a72e0f5.png", 
                        "size": "extralarge"
                    }
                ], 
                "listeners": "242965", 
                "mbid": "e6795931-6628-4f91-8509-37e74575f80b", 
                "name": "Blood on the Leaves", 
                "playcount": "1888753", 
                "streamable": {
                    "#text": "0", 
                    "fulltrack": "0"
                }, 
                "url": "https://www.last.fm/music/Kanye+West/_/Blood+on+the+Leaves"
            }, 
            {
                "artist": {
                    "mbid": "f37b3f31-b1f8-4b88-8cb5-b34f709b17d7", 
                    "name": "Iggy Pop", 
                    "url": "https://www.last.fm/music/Iggy+Pop"
                }, 
                "duration": "311", 
                "image": [
                    {
                        "#text": "https://lastfm-img2.akamaized.net/i/u/34s/fb16aed5e3084db0b2c4c3f4d79d6eae.png", 
                        "size": "small"
                    }, 
                    {
                        "#text": "https://lastfm-img2.akamaized.net/i/u/64s/fb16aed5e3084db0b2c4c3f4d79d6eae.png", 
                        "size": "medium"
                    }, 
                    {
                        "#text": "https://lastfm-img2.akamaized.net/i/u/174s/fb16aed5e3084db0b2c4c3f4d79d6eae.png", 
                        "size": "large"
                    }, 
                    {
                        "#text": "https://lastfm-img2.akamaized.net/i/u/300x300/fb16aed5e3084db0b2c4c3f4d79d6eae.png", 
                        "size": "extralarge"
                    }
                ], 
                "listeners": "547345", 
                "mbid": "20f5334d-2fbc-44b5-8429-325b7086e433", 
                "name": "Lust For Life", 
                "playcount": "2502622", 
                "streamable": {
                    "#text": "0", 
                    "fulltrack": "0"
                }, 
                "url": "https://www.last.fm/music/Iggy+Pop/_/Lust+For+Life"
            }, 
            {
                "artist": {
                    "mbid": "b41b38d4-ef3e-4f37-8c75-cfe9af999696", 
                    "name": "Cage the Elephant", 
                    "url": "https://www.last.fm/music/Cage+the+Elephant"
                }, 
                "duration": "0", 
                "image": [
                    {
                        "#text": "https://lastfm-img2.akamaized.net/i/u/34s/63b752afe8bf4cdeccf9e8dbc901c808.png", 
                        "size": "small"
                    }, 
                    {
                        "#text": "https://lastfm-img2.akamaized.net/i/u/64s/63b752afe8bf4cdeccf9e8dbc901c808.png", 
                        "size": "medium"
                    }, 
                    {
                        "#text": "https://lastfm-img2.akamaized.net/i/u/174s/63b752afe8bf4cdeccf9e8dbc901c808.png", 
                        "size": "large"
                    }, 
                    {
                        "#text": "https://lastfm-img2.akamaized.net/i/u/300x300/63b752afe8bf4cdeccf9e8dbc901c808.png", 
                        "size": "extralarge"
                    }
                ], 
                "listeners": "64250", 
                "mbid": "", 
                "name": "COLD COLD COLD", 
                "playcount": "295518", 
                "streamable": {
                    "#text": "0", 
                    "fulltrack": "0"
                }, 
                "url": "https://www.last.fm/music/Cage+the+Elephant/_/COLD+COLD+COLD"
            }, 
            {
                "artist": {
                    "mbid": "6a65d878-fcd0-42cf-aff9-ca1d636a8bcc", 
                    "name": "Foals", 
                    "url": "https://www.last.fm/music/Foals"
                }, 
                "duration": "395", 
                "image": [
                    {
                        "#text": "https://lastfm-img2.akamaized.net/i/u/34s/f7bc34403d654c2696d0e8eb153649c4.png", 
                        "size": "small"
                    }, 
                    {
                        "#text": "https://lastfm-img2.akamaized.net/i/u/64s/f7bc34403d654c2696d0e8eb153649c4.png", 
                        "size": "medium"
                    }, 
                    {
                        "#text": "https://lastfm-img2.akamaized.net/i/u/174s/f7bc34403d654c2696d0e8eb153649c4.png", 
                        "size": "large"
                    }, 
                    {
                        "#text": "https://lastfm-img2.akamaized.net/i/u/300x300/f7bc34403d654c2696d0e8eb153649c4.png", 
                        "size": "extralarge"
                    }
                ], 
                "listeners": "348669", 
                "mbid": "dbc42473-7e42-4faf-b56c-388cf2082966", 
                "name": "Spanish Sahara", 
                "playcount": "3144161", 
                "streamable": {
                    "#text": "0", 
                    "fulltrack": "0"
                }, 
                "url": "https://www.last.fm/music/Foals/_/Spanish+Sahara"
            }, 
            {
                "artist": {
                    "mbid": "596ffa74-3d08-44ef-b113-765d43d12738", 
                    "name": "Justin Timberlake", 
                    "url": "https://www.last.fm/music/Justin+Timberlake"
                }, 
                "duration": "277", 
                "image": [
                    {
                        "#text": "https://lastfm-img2.akamaized.net/i/u/34s/40d2c8b5de1f489d98036d14327f0cb1.png", 
                        "size": "small"
                    }, 
                    {
                        "#text": "https://lastfm-img2.akamaized.net/i/u/64s/40d2c8b5de1f489d98036d14327f0cb1.png", 
                        "size": "medium"
                    }, 
                    {
                        "#text": "https://lastfm-img2.akamaized.net/i/u/174s/40d2c8b5de1f489d98036d14327f0cb1.png", 
                        "size": "large"
                    }, 
                    {
                        "#text": "https://lastfm-img2.akamaized.net/i/u/300x300/40d2c8b5de1f489d98036d14327f0cb1.png", 
                        "size": "extralarge"
                    }
                ], 
                "listeners": "480595", 
                "mbid": "ac29b2ad-2aa7-4e5e-88b9-00fcb8f98131", 
                "name": "Mirrors", 
                "playcount": "4375235", 
                "streamable": {
                    "#text": "0", 
                    "fulltrack": "0"
                }, 
                "url": "https://www.last.fm/music/Justin+Timberlake/_/Mirrors"
            }, 
            {
                "artist": {
                    "mbid": "40f5d9e4-2de7-4f2d-ad41-e31a9a9fea27", 
                    "name": "The Smiths", 
                    "url": "https://www.last.fm/music/The+Smiths"
                }, 
                "duration": "0", 
                "image": [
                    {
                        "#text": "https://lastfm-img2.akamaized.net/i/u/34s/8fcb6d6f68694cffa5fda1bcfa62e621.png", 
                        "size": "small"
                    }, 
                    {
                        "#text": "https://lastfm-img2.akamaized.net/i/u/64s/8fcb6d6f68694cffa5fda1bcfa62e621.png", 
                        "size": "medium"
                    }, 
                    {
                        "#text": "https://lastfm-img2.akamaized.net/i/u/174s/8fcb6d6f68694cffa5fda1bcfa62e621.png", 
                        "size": "large"
                    }, 
                    {
                        "#text": "https://lastfm-img2.akamaized.net/i/u/300x300/8fcb6d6f68694cffa5fda1bcfa62e621.png", 
                        "size": "extralarge"
                    }
                ], 
                "listeners": "102363", 
                "mbid": "", 
                "name": "How Soon Is Now? - 2011 Remastered Version", 
                "playcount": "383063", 
                "streamable": {
                    "#text": "0", 
                    "fulltrack": "0"
                }, 
                "url": "https://www.last.fm/music/The+Smiths/_/How+Soon+Is+Now%3F+-+2011+Remastered+Version"
            }, 
            {
                "artist": {
                    "mbid": "e21857d5-3256-4547-afb3-4b6ded592596", 
                    "name": "Gorillaz", 
                    "url": "https://www.last.fm/music/Gorillaz"
                }, 
                "duration": "226", 
                "image": [
                    {
                        "#text": "https://lastfm-img2.akamaized.net/i/u/34s/dc843538aeb2c48703204fe13fde615c.png", 
                        "size": "small"
                    }, 
                    {
                        "#text": "https://lastfm-img2.akamaized.net/i/u/64s/dc843538aeb2c48703204fe13fde615c.png", 
                        "size": "medium"
                    }, 
                    {
                        "#text": "https://lastfm-img2.akamaized.net/i/u/174s/dc843538aeb2c48703204fe13fde615c.png", 
                        "size": "large"
                    }, 
                    {
                        "#text": "https://lastfm-img2.akamaized.net/i/u/300x300/dc843538aeb2c48703204fe13fde615c.png", 
                        "size": "extralarge"
                    }
                ], 
                "listeners": "696895", 
                "mbid": "806d8ff3-d1d4-4178-a524-623b87ca0c62", 
                "name": "Kids With Guns", 
                "playcount": "4006858", 
                "streamable": {
                    "#text": "0", 
                    "fulltrack": "0"
                }, 
                "url": "https://www.last.fm/music/Gorillaz/_/Kids+With+Guns"
            }, 
            {
                "artist": {
                    "mbid": "3a052c99-8c18-484a-8beb-9873b4fb3106", 
                    "name": "Iggy Azalea", 
                    "url": "https://www.last.fm/music/Iggy+Azalea"
                }, 
                "duration": "0", 
                "image": [
                    {
                        "#text": "https://lastfm-img2.akamaized.net/i/u/34s/7bee952f1c4b1db6013e3211fef07d45.png", 
                        "size": "small"
                    }, 
                    {
                        "#text": "https://lastfm-img2.akamaized.net/i/u/64s/7bee952f1c4b1db6013e3211fef07d45.png", 
                        "size": "medium"
                    }, 
                    {
                        "#text": "https://lastfm-img2.akamaized.net/i/u/174s/7bee952f1c4b1db6013e3211fef07d45.png", 
                        "size": "large"
                    }, 
                    {
                        "#text": "https://lastfm-img2.akamaized.net/i/u/300x300/7bee952f1c4b1db6013e3211fef07d45.png", 
                        "size": "extralarge"
                    }
                ], 
                "listeners": "39210", 
                "mbid": "", 
                "name": "swItCH", 
                "playcount": "423405", 
                "streamable": {
                    "#text": "0", 
                    "fulltrack": "0"
                }, 
                "url": "https://www.last.fm/music/Iggy+Azalea/_/swItCH"
            }, 
            {
                "artist": {
                    "mbid": "fa97dd36-1b82-43d7-a6e4-2adeafd59cef", 
                    "name": "Fleet Foxes", 
                    "url": "https://www.last.fm/music/Fleet+Foxes"
                }, 
                "duration": "280", 
                "image": [
                    {
                        "#text": "https://lastfm-img2.akamaized.net/i/u/34s/b52deeb0f35d4e8a9fef96cdf9a63c74.png", 
                        "size": "small"
                    }, 
                    {
                        "#text": "https://lastfm-img2.akamaized.net/i/u/64s/b52deeb0f35d4e8a9fef96cdf9a63c74.png", 
                        "size": "medium"
                    }, 
                    {
                        "#text": "https://lastfm-img2.akamaized.net/i/u/174s/b52deeb0f35d4e8a9fef96cdf9a63c74.png", 
                        "size": "large"
                    }, 
                    {
                        "#text": "https://lastfm-img2.akamaized.net/i/u/300x300/b52deeb0f35d4e8a9fef96cdf9a63c74.png", 
                        "size": "extralarge"
                    }
                ], 
                "listeners": "450937", 
                "mbid": "310fa155-f188-46bb-b39a-f5ab8ac048df", 
                "name": "Blue Ridge Mountains", 
                "playcount": "3150282", 
                "streamable": {
                    "#text": "0", 
                    "fulltrack": "0"
                }, 
                "url": "https://www.last.fm/music/Fleet+Foxes/_/Blue+Ridge+Mountains"
            }, 
            {
                "artist": {
                    "mbid": "f59c5520-5f46-4d2c-b2c4-822eabf53419", 
                    "name": "Linkin Park", 
                    "url": "https://www.last.fm/music/Linkin+Park"
                }, 
                "duration": "0", 
                "image": [
                    {
                        "#text": "https://lastfm-img2.akamaized.net/i/u/34s/8425d15256d9702ef5d611210a6d2709.png", 
                        "size": "small"
                    }, 
                    {
                        "#text": "https://lastfm-img2.akamaized.net/i/u/64s/8425d15256d9702ef5d611210a6d2709.png", 
                        "size": "medium"
                    }, 
                    {
                        "#text": "https://lastfm-img2.akamaized.net/i/u/174s/8425d15256d9702ef5d611210a6d2709.png", 
                        "size": "large"
                    }, 
                    {
                        "#text": "https://lastfm-img2.akamaized.net/i/u/300x300/8425d15256d9702ef5d611210a6d2709.png", 
                        "size": "extralarge"
                    }
                ], 
                "listeners": "7438", 
                "mbid": "", 
                "name": "One More Light - Steve Aoki Chester Forever Remix", 
                "playcount": "15894", 
                "streamable": {
                    "#text": "0", 
                    "fulltrack": "0"
                }, 
                "url": "https://www.last.fm/music/Linkin+Park/_/One+More+Light+-+Steve+Aoki+Chester+Forever+Remix"
            }, 
            {
                "artist": {
                    "mbid": "c44ff8d1-8c81-45c8-abd6-5feefb07b764", 
                    "name": "Interpol", 
                    "url": "https://www.last.fm/music/Interpol"
                }, 
                "duration": "300", 
                "image": [
                    {
                        "#text": "https://lastfm-img2.akamaized.net/i/u/34s/090f3d2d9568411896963a83830cffc3.png", 
                        "size": "small"
                    }, 
                    {
                        "#text": "https://lastfm-img2.akamaized.net/i/u/64s/090f3d2d9568411896963a83830cffc3.png", 
                        "size": "medium"
                    }, 
                    {
                        "#text": "https://lastfm-img2.akamaized.net/i/u/174s/090f3d2d9568411896963a83830cffc3.png", 
                        "size": "large"
                    }, 
                    {
                        "#text": "https://lastfm-img2.akamaized.net/i/u/300x300/090f3d2d9568411896963a83830cffc3.png", 
                        "size": "extralarge"
                    }
                ], 
                "listeners": "479011", 
                "mbid": "56228aad-af59-4f26-9e20-34b30a529312", 
                "name": "Rest My Chemistry", 
                "playcount": "2895655", 
                "streamable": {
                    "#text": "0", 
                    "fulltrack": "0"
                }, 
                "url": "https://www.last.fm/music/Interpol/_/Rest+My+Chemistry"
            }, 
            {
                "artist": {
                    "mbid": "153c9281-268f-4cf3-8938-f5a4593e5df4", 
                    "name": "Soundgarden", 
                    "url": "https://www.last.fm/music/Soundgarden"
                }, 
                "duration": "263", 
                "image": [
                    {
                        "#text": "https://lastfm-img2.akamaized.net/i/u/34s/9f28044406774eb2b61d594245015dc0.png", 
                        "size": "small"
                    }, 
                    {
                        "#text": "https://lastfm-img2.akamaized.net/i/u/64s/9f28044406774eb2b61d594245015dc0.png", 
                        "size": "medium"
                    }, 
                    {
                        "#text": "https://lastfm-img2.akamaized.net/i/u/174s/9f28044406774eb2b61d594245015dc0.png", 
                        "size": "large"
                    }, 
                    {
                        "#text": "https://lastfm-img2.akamaized.net/i/u/300x300/9f28044406774eb2b61d594245015dc0.png", 
                        "size": "extralarge"
                    }
                ], 
                "listeners": "476954", 
                "mbid": "b41903dc-0bc5-4498-bc44-7b9658b36983", 
                "name": "Spoonman", 
                "playcount": "2054219", 
                "streamable": {
                    "#text": "0", 
                    "fulltrack": "0"
                }, 
                "url": "https://www.last.fm/music/Soundgarden/_/Spoonman"
            }, 
            {
                "artist": {
                    "mbid": "3599cf21-2ed3-405d-a1f1-b52ff7b28df8", 
                    "name": "Kelela", 
                    "url": "https://www.last.fm/music/Kelela"
                }, 
                "duration": "0", 
                "image": [
                    {
                        "#text": "https://lastfm-img2.akamaized.net/i/u/34s/60b7b0c39f52f19c83ce873ad62f1773.png", 
                        "size": "small"
                    }, 
                    {
                        "#text": "https://lastfm-img2.akamaized.net/i/u/64s/60b7b0c39f52f19c83ce873ad62f1773.png", 
                        "size": "medium"
                    }, 
                    {
                        "#text": "https://lastfm-img2.akamaized.net/i/u/174s/60b7b0c39f52f19c83ce873ad62f1773.png", 
                        "size": "large"
                    }, 
                    {
                        "#text": "https://lastfm-img2.akamaized.net/i/u/300x300/60b7b0c39f52f19c83ce873ad62f1773.png", 
                        "size": "extralarge"
                    }
                ], 
                "listeners": "17310", 
                "mbid": "", 
                "name": "Waitin", 
                "playcount": "66521", 
                "streamable": {
                    "#text": "0", 
                    "fulltrack": "0"
                }, 
                "url": "https://www.last.fm/music/Kelela/_/Waitin"
            }, 
            {
                "artist": {
                    "mbid": "d6e0e274-8e19-44ce-b5b2-52c12f8a674a", 
                    "name": "Led Zeppelin", 
                    "url": "https://www.last.fm/music/Led+Zeppelin"
                }, 
                "duration": "430", 
                "image": [
                    {
                        "#text": "https://lastfm-img2.akamaized.net/i/u/34s/8b238225c5f341dfc10a1695a9cdf00c.png", 
                        "size": "small"
                    }, 
                    {
                        "#text": "https://lastfm-img2.akamaized.net/i/u/64s/8b238225c5f341dfc10a1695a9cdf00c.png", 
                        "size": "medium"
                    }, 
                    {
                        "#text": "https://lastfm-img2.akamaized.net/i/u/174s/8b238225c5f341dfc10a1695a9cdf00c.png", 
                        "size": "large"
                    }, 
                    {
                        "#text": "https://lastfm-img2.akamaized.net/i/u/300x300/8b238225c5f341dfc10a1695a9cdf00c.png", 
                        "size": "extralarge"
                    }
                ], 
                "listeners": "567506", 
                "mbid": "61fac487-6c27-4c18-8dab-1e82c6abb52b", 
                "name": "When the Levee Breaks", 
                "playcount": "3402561", 
                "streamable": {
                    "#text": "0", 
                    "fulltrack": "0"
                }, 
                "url": "https://www.last.fm/music/Led+Zeppelin/_/When+the+Levee+Breaks"
            }, 
            {
                "artist": {
                    "mbid": "", 
                    "name": "BROCKHAMPTON", 
                    "url": "https://www.last.fm/music/BROCKHAMPTON"
                }, 
                "duration": "0", 
                "image": [
                    {
                        "#text": "https://lastfm-img2.akamaized.net/i/u/34s/b3f81dac5ff7475eb2383506e3c5856c.png", 
                        "size": "small"
                    }, 
                    {
                        "#text": "https://lastfm-img2.akamaized.net/i/u/64s/b3f81dac5ff7475eb2383506e3c5856c.png", 
                        "size": "medium"
                    }, 
                    {
                        "#text": "https://lastfm-img2.akamaized.net/i/u/174s/b3f81dac5ff7475eb2383506e3c5856c.png", 
                        "size": "large"
                    }, 
                    {
                        "#text": "https://lastfm-img2.akamaized.net/i/u/300x300/b3f81dac5ff7475eb2383506e3c5856c.png", 
                        "size": "extralarge"
                    }
                ], 
                "listeners": "19303", 
                "mbid": "", 
                "name": "JUNKY", 
                "playcount": "145423", 
                "streamable": {
                    "#text": "0", 
                    "fulltrack": "0"
                }, 
                "url": "https://www.last.fm/music/BROCKHAMPTON/_/JUNKY"
            }, 
            {
                "artist": {
                    "mbid": "c8b03190-306c-4120-bb0b-6f2ebfc06ea9", 
                    "name": "The Weeknd", 
                    "url": "https://www.last.fm/music/The+Weeknd"
                }, 
                "duration": "0", 
                "image": [
                    {
                        "#text": "https://lastfm-img2.akamaized.net/i/u/34s/88034451e014e1fa51f0c15634fedf6d.png", 
                        "size": "small"
                    }, 
                    {
                        "#text": "https://lastfm-img2.akamaized.net/i/u/64s/88034451e014e1fa51f0c15634fedf6d.png", 
                        "size": "medium"
                    }, 
                    {
                        "#text": "https://lastfm-img2.akamaized.net/i/u/174s/88034451e014e1fa51f0c15634fedf6d.png", 
                        "size": "large"
                    }, 
                    {
                        "#text": "https://lastfm-img2.akamaized.net/i/u/300x300/88034451e014e1fa51f0c15634fedf6d.png", 
                        "size": "extralarge"
                    }
                ], 
                "listeners": "106434", 
                "mbid": "", 
                "name": "False Alarm", 
                "playcount": "684353", 
                "streamable": {
                    "#text": "0", 
                    "fulltrack": "0"
                }, 
                "url": "https://www.last.fm/music/The+Weeknd/_/False+Alarm"
            }, 
            {
                "artist": {
                    "mbid": "a16371b9-7d36-497a-a9d4-42b0a0440c5e", 
                    "name": "Slowdive", 
                    "url": "https://www.last.fm/music/Slowdive"
                }, 
                "duration": "0", 
                "image": [
                    {
                        "#text": "https://lastfm-img2.akamaized.net/i/u/34s/6117351f898b4a90caed5444b8772bac.png", 
                        "size": "small"
                    }, 
                    {
                        "#text": "https://lastfm-img2.akamaized.net/i/u/64s/6117351f898b4a90caed5444b8772bac.png", 
                        "size": "medium"
                    }, 
                    {
                        "#text": "https://lastfm-img2.akamaized.net/i/u/174s/6117351f898b4a90caed5444b8772bac.png", 
                        "size": "large"
                    }, 
                    {
                        "#text": "https://lastfm-img2.akamaized.net/i/u/300x300/6117351f898b4a90caed5444b8772bac.png", 
                        "size": "extralarge"
                    }
                ], 
                "listeners": "44081", 
                "mbid": "", 
                "name": "No Longer Making Time", 
                "playcount": "187494", 
                "streamable": {
                    "#text": "0", 
                    "fulltrack": "0"
                }, 
                "url": "https://www.last.fm/music/Slowdive/_/No+Longer+Making+Time"
            }, 
            {
                "artist": {
                    "mbid": "a74b1b7f-71a5-4011-9441-d0b5e4122711", 
                    "name": "Radiohead", 
                    "url": "https://www.last.fm/music/Radiohead"
                }, 
                "duration": "267", 
                "image": [
                    {
                        "#text": "https://lastfm-img2.akamaized.net/i/u/34s/97a3e5ec1a56662d6100a02343944c95.png", 
                        "size": "small"
                    }, 
                    {
                        "#text": "https://lastfm-img2.akamaized.net/i/u/64s/97a3e5ec1a56662d6100a02343944c95.png", 
                        "size": "medium"
                    }, 
                    {
                        "#text": "https://lastfm-img2.akamaized.net/i/u/174s/97a3e5ec1a56662d6100a02343944c95.png", 
                        "size": "large"
                    }, 
                    {
                        "#text": "https://lastfm-img2.akamaized.net/i/u/300x300/97a3e5ec1a56662d6100a02343944c95.png", 
                        "size": "extralarge"
                    }
                ], 
                "listeners": "815905", 
                "mbid": "bd82738d-163c-4b1a-bfaf-7acffe30e68a", 
                "name": "Subterranean Homesick Alien", 
                "playcount": "5080424", 
                "streamable": {
                    "#text": "0", 
                    "fulltrack": "0"
                }, 
                "url": "https://www.last.fm/music/Radiohead/_/Subterranean+Homesick+Alien"
            }, 
            {
                "artist": {
                    "mbid": "122d63fc-8671-43e4-9752-34e846d62a9c", 
                    "name": "Katy Perry", 
                    "url": "https://www.last.fm/music/Katy+Perry"
                }, 
                "duration": "0", 
                "image": [
                    {
                        "#text": "https://lastfm-img2.akamaized.net/i/u/34s/ce868ba9f1f45568c51d6142b07296d2.png", 
                        "size": "small"
                    }, 
                    {
                        "#text": "https://lastfm-img2.akamaized.net/i/u/64s/ce868ba9f1f45568c51d6142b07296d2.png", 
                        "size": "medium"
                    }, 
                    {
                        "#text": "https://lastfm-img2.akamaized.net/i/u/174s/ce868ba9f1f45568c51d6142b07296d2.png", 
                        "size": "large"
                    }, 
                    {
                        "#text": "https://lastfm-img2.akamaized.net/i/u/300x300/ce868ba9f1f45568c51d6142b07296d2.png", 
                        "size": "extralarge"
                    }
                ], 
                "listeners": "41355", 
                "mbid": "", 
                "name": "Witness", 
                "playcount": "450126", 
                "streamable": {
                    "#text": "0", 
                    "fulltrack": "0"
                }, 
                "url": "https://www.last.fm/music/Katy+Perry/_/Witness"
            }, 
            {
                "artist": {
                    "mbid": "c954d136-c7fd-4fd9-8bb0-fb0491fc6a02", 
                    "name": "Nena", 
                    "url": "https://www.last.fm/music/Nena"
                }, 
                "duration": "235", 
                "image": [
                    {
                        "#text": "https://lastfm-img2.akamaized.net/i/u/34s/31e4f786843c450eb574c9af64b7dcf5.png", 
                        "size": "small"
                    }, 
                    {
                        "#text": "https://lastfm-img2.akamaized.net/i/u/64s/31e4f786843c450eb574c9af64b7dcf5.png", 
                        "size": "medium"
                    }, 
                    {
                        "#text": "https://lastfm-img2.akamaized.net/i/u/174s/31e4f786843c450eb574c9af64b7dcf5.png", 
                        "size": "large"
                    }, 
                    {
                        "#text": "https://lastfm-img2.akamaized.net/i/u/300x300/31e4f786843c450eb574c9af64b7dcf5.png", 
                        "size": "extralarge"
                    }
                ], 
                "listeners": "336334", 
                "mbid": "938438b3-1360-4eac-a815-7ff9ca921008", 
                "name": "99 Luftballons", 
                "playcount": "1454727", 
                "streamable": {
                    "#text": "0", 
                    "fulltrack": "0"
                }, 
                "url": "https://www.last.fm/music/Nena/_/99+Luftballons"
            }, 
            {
                "artist": {
                    "mbid": "", 
                    "name": "LIL UZI VERT", 
                    "url": "https://www.last.fm/music/LIL+UZI+VERT"
                }, 
                "duration": "0", 
                "image": [
                    {
                        "#text": "https://lastfm-img2.akamaized.net/i/u/34s/b554d07e2cdaefa48e816ca453cf84ff.png", 
                        "size": "small"
                    }, 
                    {
                        "#text": "https://lastfm-img2.akamaized.net/i/u/64s/b554d07e2cdaefa48e816ca453cf84ff.png", 
                        "size": "medium"
                    }, 
                    {
                        "#text": "https://lastfm-img2.akamaized.net/i/u/174s/b554d07e2cdaefa48e816ca453cf84ff.png", 
                        "size": "large"
                    }, 
                    {
                        "#text": "https://lastfm-img2.akamaized.net/i/u/300x300/b554d07e2cdaefa48e816ca453cf84ff.png", 
                        "size": "extralarge"
                    }
                ], 
                "listeners": "7313", 
                "mbid": "", 
                "name": "The Way Life Goes (feat. Nicki Minaj & Oh Wonder) - Remix", 
                "playcount": "18689", 
                "streamable": {
                    "#text": "0", 
                    "fulltrack": "0"
                }, 
                "url": "https://www.last.fm/music/LIL+UZI+VERT/_/The+Way+Life+Goes+(feat.+Nicki+Minaj+&+Oh+Wonder)+-+Remix"
            }, 
            {
                "artist": {
                    "mbid": "", 
                    "name": "Lil' Wayne", 
                    "url": "https://www.last.fm/music/Lil%27+Wayne"
                }, 
                "duration": "0", 
                "image": [
                    {
                        "#text": "https://lastfm-img2.akamaized.net/i/u/34s/97fceb73d43743539060f2601d3a730a.png", 
                        "size": "small"
                    }, 
                    {
                        "#text": "https://lastfm-img2.akamaized.net/i/u/64s/97fceb73d43743539060f2601d3a730a.png", 
                        "size": "medium"
                    }, 
                    {
                        "#text": "https://lastfm-img2.akamaized.net/i/u/174s/97fceb73d43743539060f2601d3a730a.png", 
                        "size": "large"
                    }, 
                    {
                        "#text": "https://lastfm-img2.akamaized.net/i/u/300x300/97fceb73d43743539060f2601d3a730a.png", 
                        "size": "extralarge"
                    }
                ], 
                "listeners": "96165", 
                "mbid": "", 
                "name": "Sucker For Pain (with Wiz Khalifa, Imagine Dragons, Logic & Ty Dolla $ign feat. X Ambassadors)", 
                "playcount": "462982", 
                "streamable": {
                    "#text": "0", 
                    "fulltrack": "0"
                }, 
                "url": "https://www.last.fm/music/Lil%27+Wayne/_/Sucker+For+Pain+(with+Wiz+Khalifa,+Imagine+Dragons,+Logic+&+Ty+Dolla+$ign+feat.+X+Ambassadors)"
            }, 
            {
                "artist": {
                    "mbid": "63aa26c3-d59b-4da4-84ac-716b54f1ef4d", 
                    "name": "Tame Impala", 
                    "url": "https://www.last.fm/music/Tame+Impala"
                }, 
                "duration": "271", 
                "image": [
                    {
                        "#text": "https://lastfm-img2.akamaized.net/i/u/34s/6990c1baa121453c66ae91008e7e2a2a.png", 
                        "size": "small"
                    }, 
                    {
                        "#text": "https://lastfm-img2.akamaized.net/i/u/64s/6990c1baa121453c66ae91008e7e2a2a.png", 
                        "size": "medium"
                    }, 
                    {
                        "#text": "https://lastfm-img2.akamaized.net/i/u/174s/6990c1baa121453c66ae91008e7e2a2a.png", 
                        "size": "large"
                    }, 
                    {
                        "#text": "https://lastfm-img2.akamaized.net/i/u/300x300/6990c1baa121453c66ae91008e7e2a2a.png", 
                        "size": "extralarge"
                    }
                ], 
                "listeners": "298657", 
                "mbid": "a282bde7-10fb-4ef4-983d-067a9ae8be4a", 
                "name": "Mind Mischief", 
                "playcount": "2163686", 
                "streamable": {
                    "#text": "0", 
                    "fulltrack": "0"
                }, 
                "url": "https://www.last.fm/music/Tame+Impala/_/Mind+Mischief"
            }, 
            {
                "artist": {
                    "mbid": "b95ce3ff-3d05-4e87-9e01-c97b66af13d4", 
                    "name": "Eminem", 
                    "url": "https://www.last.fm/music/Eminem"
                }, 
                "duration": "424", 
                "image": [
                    {
                        "#text": "https://lastfm-img2.akamaized.net/i/u/34s/72e17aea585344a8914178d3fdfdd980.png", 
                        "size": "small"
                    }, 
                    {
                        "#text": "https://lastfm-img2.akamaized.net/i/u/64s/72e17aea585344a8914178d3fdfdd980.png", 
                        "size": "medium"
                    }, 
                    {
                        "#text": "https://lastfm-img2.akamaized.net/i/u/174s/72e17aea585344a8914178d3fdfdd980.png", 
                        "size": "large"
                    }, 
                    {
                        "#text": "https://lastfm-img2.akamaized.net/i/u/300x300/72e17aea585344a8914178d3fdfdd980.png", 
                        "size": "extralarge"
                    }
                ], 
                "listeners": "562331", 
                "mbid": "61b4d5d8-8c97-4014-bd74-3ba6acd0479d", 
                "name": "My Name Is", 
                "playcount": "2301408", 
                "streamable": {
                    "#text": "0", 
                    "fulltrack": "0"
                }, 
                "url": "https://www.last.fm/music/Eminem/_/My+Name+Is"
            }, 
            {
                "artist": {
                    "mbid": "5882e375-503f-4bd2-89b1-967e0bfcb199", 
                    "name": "Ariel Pink", 
                    "url": "https://www.last.fm/music/Ariel+Pink"
                }, 
                "duration": "0", 
                "image": [
                    {
                        "#text": "https://lastfm-img2.akamaized.net/i/u/34s/38b84b38c8af4c123621e2f4b9a9c19f.png", 
                        "size": "small"
                    }, 
                    {
                        "#text": "https://lastfm-img2.akamaized.net/i/u/64s/38b84b38c8af4c123621e2f4b9a9c19f.png", 
                        "size": "medium"
                    }, 
                    {
                        "#text": "https://lastfm-img2.akamaized.net/i/u/174s/38b84b38c8af4c123621e2f4b9a9c19f.png", 
                        "size": "large"
                    }, 
                    {
                        "#text": "https://lastfm-img2.akamaized.net/i/u/300x300/38b84b38c8af4c123621e2f4b9a9c19f.png", 
                        "size": "extralarge"
                    }
                ], 
                "listeners": "25234", 
                "mbid": "", 
                "name": "Another Weekend", 
                "playcount": "87631", 
                "streamable": {
                    "#text": "0", 
                    "fulltrack": "0"
                }, 
                "url": "https://www.last.fm/music/Ariel+Pink/_/Another+Weekend"
            }, 
            {
                "artist": {
                    "mbid": "f1106b17-dcbb-45f6-b938-199ccfab50cc", 
                    "name": "New Order", 
                    "url": "https://www.last.fm/music/New+Order"
                }, 
                "duration": "272", 
                "image": [
                    {
                        "#text": "https://lastfm-img2.akamaized.net/i/u/34s/8369b21a2af5c2b59199af2e02b1c276.png", 
                        "size": "small"
                    }, 
                    {
                        "#text": "https://lastfm-img2.akamaized.net/i/u/64s/8369b21a2af5c2b59199af2e02b1c276.png", 
                        "size": "medium"
                    }, 
                    {
                        "#text": "https://lastfm-img2.akamaized.net/i/u/174s/8369b21a2af5c2b59199af2e02b1c276.png", 
                        "size": "large"
                    }, 
                    {
                        "#text": "https://lastfm-img2.akamaized.net/i/u/300x300/8369b21a2af5c2b59199af2e02b1c276.png", 
                        "size": "extralarge"
                    }
                ], 
                "listeners": "405824", 
                "mbid": "36a04874-5868-4f4f-8d97-624a7a0ab4b6", 
                "name": "Bizarre Love Triangle", 
                "playcount": "2508724", 
                "streamable": {
                    "#text": "0", 
                    "fulltrack": "0"
                }, 
                "url": "https://www.last.fm/music/New+Order/_/Bizarre+Love+Triangle"
            }, 
            {
                "artist": {
                    "mbid": "6d7b7cd4-254b-4c25-83f6-dd20f98ceacd", 
                    "name": "M83", 
                    "url": "https://www.last.fm/music/M83"
                }, 
                "duration": "343", 
                "image": [
                    {
                        "#text": "https://lastfm-img2.akamaized.net/i/u/34s/c45547e71f3047e78ca72562bad477a5.png", 
                        "size": "small"
                    }, 
                    {
                        "#text": "https://lastfm-img2.akamaized.net/i/u/64s/c45547e71f3047e78ca72562bad477a5.png", 
                        "size": "medium"
                    }, 
                    {
                        "#text": "https://lastfm-img2.akamaized.net/i/u/174s/c45547e71f3047e78ca72562bad477a5.png", 
                        "size": "large"
                    }, 
                    {
                        "#text": "https://lastfm-img2.akamaized.net/i/u/300x300/c45547e71f3047e78ca72562bad477a5.png", 
                        "size": "extralarge"
                    }
                ], 
                "listeners": "418272", 
                "mbid": "9bfa18fd-2dbc-44f9-8048-d86f39dc354c", 
                "name": "Wait", 
                "playcount": "2725466", 
                "streamable": {
                    "#text": "0", 
                    "fulltrack": "0"
                }, 
                "url": "https://www.last.fm/music/M83/_/Wait"
            }, 
            {
                "artist": {
                    "mbid": "", 
                    "name": "Petit biscuit", 
                    "url": "https://www.last.fm/music/Petit+biscuit"
                }, 
                "duration": "0", 
                "image": [
                    {
                        "#text": "https://lastfm-img2.akamaized.net/i/u/34s/671179ef72afe56ca167b558208972bd.png", 
                        "size": "small"
                    }, 
                    {
                        "#text": "https://lastfm-img2.akamaized.net/i/u/64s/671179ef72afe56ca167b558208972bd.png", 
                        "size": "medium"
                    }, 
                    {
                        "#text": "https://lastfm-img2.akamaized.net/i/u/174s/671179ef72afe56ca167b558208972bd.png", 
                        "size": "large"
                    }, 
                    {
                        "#text": "https://lastfm-img2.akamaized.net/i/u/300x300/671179ef72afe56ca167b558208972bd.png", 
                        "size": "extralarge"
                    }
                ], 
                "listeners": "13655", 
                "mbid": "", 
                "name": "Waterfall", 
                "playcount": "29305", 
                "streamable": {
                    "#text": "0", 
                    "fulltrack": "0"
                }, 
                "url": "https://www.last.fm/music/Petit+biscuit/_/Waterfall"
            }, 
            {
                "artist": {
                    "mbid": "481bf5f9-2e7c-4c44-b08a-05b32bc7c00d", 
                    "name": "INXS", 
                    "url": "https://www.last.fm/music/INXS"
                }, 
                "duration": "182", 
                "image": [
                    {
                        "#text": "https://lastfm-img2.akamaized.net/i/u/34s/bc7c66a2468749e2946df52e1073407e.png", 
                        "size": "small"
                    }, 
                    {
                        "#text": "https://lastfm-img2.akamaized.net/i/u/64s/bc7c66a2468749e2946df52e1073407e.png", 
                        "size": "medium"
                    }, 
                    {
                        "#text": "https://lastfm-img2.akamaized.net/i/u/174s/bc7c66a2468749e2946df52e1073407e.png", 
                        "size": "large"
                    }, 
                    {
                        "#text": "https://lastfm-img2.akamaized.net/i/u/300x300/bc7c66a2468749e2946df52e1073407e.png", 
                        "size": "extralarge"
                    }
                ], 
                "listeners": "353506", 
                "mbid": "619ee3de-edef-4370-9373-02d90b1ccbb7", 
                "name": "Never Tear Us Apart", 
                "playcount": "1768726", 
                "streamable": {
                    "#text": "0", 
                    "fulltrack": "0"
                }, 
                "url": "https://www.last.fm/music/INXS/_/Never+Tear+Us+Apart"
            }, 
            {
                "artist": {
                    "mbid": "fc7bbf00-fbaa-4736-986b-b3ac0266ca9b", 
                    "name": "alt-J", 
                    "url": "https://www.last.fm/music/alt-J"
                }, 
                "duration": "0", 
                "image": [
                    {
                        "#text": "https://lastfm-img2.akamaized.net/i/u/34s/bf2571ed95b92afd6d5ee5c49ac97b06.png", 
                        "size": "small"
                    }, 
                    {
                        "#text": "https://lastfm-img2.akamaized.net/i/u/64s/bf2571ed95b92afd6d5ee5c49ac97b06.png", 
                        "size": "medium"
                    }, 
                    {
                        "#text": "https://lastfm-img2.akamaized.net/i/u/174s/bf2571ed95b92afd6d5ee5c49ac97b06.png", 
                        "size": "large"
                    }, 
                    {
                        "#text": "https://lastfm-img2.akamaized.net/i/u/300x300/bf2571ed95b92afd6d5ee5c49ac97b06.png", 
                        "size": "extralarge"
                    }
                ], 
                "listeners": "383042", 
                "mbid": "eeb3259b-0c9e-4564-ac86-399a6d748627", 
                "name": "Fitzpleasure", 
                "playcount": "3294293", 
                "streamable": {
                    "#text": "0", 
                    "fulltrack": "0"
                }, 
                "url": "https://www.last.fm/music/alt-J/_/Fitzpleasure"
            }, 
            {
                "artist": {
                    "mbid": "", 
                    "name": "xxxtentacion", 
                    "url": "https://www.last.fm/music/xxxtentacion"
                }, 
                "duration": "0", 
                "image": [
                    {
                        "#text": "https://lastfm-img2.akamaized.net/i/u/34s/42387909bbfcbfea9eec91d5aceec1d8.png", 
                        "size": "small"
                    }, 
                    {
                        "#text": "https://lastfm-img2.akamaized.net/i/u/64s/42387909bbfcbfea9eec91d5aceec1d8.png", 
                        "size": "medium"
                    }, 
                    {
                        "#text": "https://lastfm-img2.akamaized.net/i/u/174s/42387909bbfcbfea9eec91d5aceec1d8.png", 
                        "size": "large"
                    }, 
                    {
                        "#text": "https://lastfm-img2.akamaized.net/i/u/300x300/42387909bbfcbfea9eec91d5aceec1d8.png", 
                        "size": "extralarge"
                    }
                ], 
                "listeners": "28455", 
                "mbid": "", 
                "name": "Revenge", 
                "playcount": "227420", 
                "streamable": {
                    "#text": "0", 
                    "fulltrack": "0"
                }, 
                "url": "https://www.last.fm/music/xxxtentacion/_/Revenge"
            }, 
            {
                "artist": {
                    "mbid": "", 
                    "name": "BROCKHAMPTON", 
                    "url": "https://www.last.fm/music/BROCKHAMPTON"
                }, 
                "duration": "0", 
                "image": [
                    {
                        "#text": "https://lastfm-img2.akamaized.net/i/u/34s/b3f81dac5ff7475eb2383506e3c5856c.png", 
                        "size": "small"
                    }, 
                    {
                        "#text": "https://lastfm-img2.akamaized.net/i/u/64s/b3f81dac5ff7475eb2383506e3c5856c.png", 
                        "size": "medium"
                    }, 
                    {
                        "#text": "https://lastfm-img2.akamaized.net/i/u/174s/b3f81dac5ff7475eb2383506e3c5856c.png", 
                        "size": "large"
                    }, 
                    {
                        "#text": "https://lastfm-img2.akamaized.net/i/u/300x300/b3f81dac5ff7475eb2383506e3c5856c.png", 
                        "size": "extralarge"
                    }
                ], 
                "listeners": "19761", 
                "mbid": "", 
                "name": "JELLO", 
                "playcount": "124342", 
                "streamable": {
                    "#text": "0", 
                    "fulltrack": "0"
                }, 
                "url": "https://www.last.fm/music/BROCKHAMPTON/_/JELLO"
            }, 
            {
                "artist": {
                    "mbid": "bfcb6630-9b31-4e63-b11f-7b0363be72b5", 
                    "name": "The Lumineers", 
                    "url": "https://www.last.fm/music/The+Lumineers"
                }, 
                "duration": "279", 
                "image": [
                    {
                        "#text": "https://lastfm-img2.akamaized.net/i/u/34s/03e320dd70c0577c42c459eac0063c16.png", 
                        "size": "small"
                    }, 
                    {
                        "#text": "https://lastfm-img2.akamaized.net/i/u/64s/03e320dd70c0577c42c459eac0063c16.png", 
                        "size": "medium"
                    }, 
                    {
                        "#text": "https://lastfm-img2.akamaized.net/i/u/174s/03e320dd70c0577c42c459eac0063c16.png", 
                        "size": "large"
                    }, 
                    {
                        "#text": "https://lastfm-img2.akamaized.net/i/u/300x300/03e320dd70c0577c42c459eac0063c16.png", 
                        "size": "extralarge"
                    }
                ], 
                "listeners": "397942", 
                "mbid": "ab403101-8383-405c-a477-758797b1fd98", 
                "name": "Stubborn Love", 
                "playcount": "2624520", 
                "streamable": {
                    "#text": "0", 
                    "fulltrack": "0"
                }, 
                "url": "https://www.last.fm/music/The+Lumineers/_/Stubborn+Love"
            }, 
            {
                "artist": {
                    "mbid": "aadee541-1990-41df-b8a9-38ac679435ec", 
                    "name": "Royal Blood", 
                    "url": "https://www.last.fm/music/Royal+Blood"
                }, 
                "duration": "0", 
                "image": [
                    {
                        "#text": "https://lastfm-img2.akamaized.net/i/u/34s/678b5072eb39fa96d6c77a50659d67d0.png", 
                        "size": "small"
                    }, 
                    {
                        "#text": "https://lastfm-img2.akamaized.net/i/u/64s/678b5072eb39fa96d6c77a50659d67d0.png", 
                        "size": "medium"
                    }, 
                    {
                        "#text": "https://lastfm-img2.akamaized.net/i/u/174s/678b5072eb39fa96d6c77a50659d67d0.png", 
                        "size": "large"
                    }, 
                    {
                        "#text": "https://lastfm-img2.akamaized.net/i/u/300x300/678b5072eb39fa96d6c77a50659d67d0.png", 
                        "size": "extralarge"
                    }
                ], 
                "listeners": "40596", 
                "mbid": "", 
                "name": "Hook, Line & Sinker", 
                "playcount": "182287", 
                "streamable": {
                    "#text": "0", 
                    "fulltrack": "0"
                }, 
                "url": "https://www.last.fm/music/Royal+Blood/_/Hook,+Line+&+Sinker"
            }, 
            {
                "artist": {
                    "mbid": "9e53f84d-ef44-4c16-9677-5fd4d78cbd7d", 
                    "name": "Wilco", 
                    "url": "https://www.last.fm/music/Wilco"
                }, 
                "duration": "276", 
                "image": [
                    {
                        "#text": "https://lastfm-img2.akamaized.net/i/u/34s/5f56c44ac6744d938d220e93303df4ac.png", 
                        "size": "small"
                    }, 
                    {
                        "#text": "https://lastfm-img2.akamaized.net/i/u/64s/5f56c44ac6744d938d220e93303df4ac.png", 
                        "size": "medium"
                    }, 
                    {
                        "#text": "https://lastfm-img2.akamaized.net/i/u/174s/5f56c44ac6744d938d220e93303df4ac.png", 
                        "size": "large"
                    }, 
                    {
                        "#text": "https://lastfm-img2.akamaized.net/i/u/300x300/5f56c44ac6744d938d220e93303df4ac.png", 
                        "size": "extralarge"
                    }
                ], 
                "listeners": "369320", 
                "mbid": "dadeaa1b-b997-4b35-a53c-24dd8b2b144f", 
                "name": "Jesus, Etc.", 
                "playcount": "2553113", 
                "streamable": {
                    "#text": "0", 
                    "fulltrack": "0"
                }, 
                "url": "https://www.last.fm/music/Wilco/_/Jesus,+Etc."
            }, 
            {
                "artist": {
                    "mbid": "4d2956d1-a3f7-44bb-9a41-67563e1a0c94", 
                    "name": "Blondie", 
                    "url": "https://www.last.fm/music/Blondie"
                }, 
                "duration": "205", 
                "image": [
                    {
                        "#text": "https://lastfm-img2.akamaized.net/i/u/34s/0dd76cf894724b6bb06064a4247a261a.png", 
                        "size": "small"
                    }, 
                    {
                        "#text": "https://lastfm-img2.akamaized.net/i/u/64s/0dd76cf894724b6bb06064a4247a261a.png", 
                        "size": "medium"
                    }, 
                    {
                        "#text": "https://lastfm-img2.akamaized.net/i/u/174s/0dd76cf894724b6bb06064a4247a261a.png", 
                        "size": "large"
                    }, 
                    {
                        "#text": "https://lastfm-img2.akamaized.net/i/u/300x300/0dd76cf894724b6bb06064a4247a261a.png", 
                        "size": "extralarge"
                    }
                ], 
                "listeners": "507429", 
                "mbid": "5aca0e28-b3dc-42b8-8d48-6af35332addc", 
                "name": "Call Me", 
                "playcount": "2342155", 
                "streamable": {
                    "#text": "0", 
                    "fulltrack": "0"
                }, 
                "url": "https://www.last.fm/music/Blondie/_/Call+Me"
            }, 
            {
                "artist": {
                    "mbid": "7e9bd05a-117f-4cce-87bc-e011527a8b18", 
                    "name": "Miley Cyrus", 
                    "url": "https://www.last.fm/music/Miley+Cyrus"
                }, 
                "duration": "0", 
                "image": [
                    {
                        "#text": "https://lastfm-img2.akamaized.net/i/u/34s/1ab2389a384128536c3df2d79d736c43.png", 
                        "size": "small"
                    }, 
                    {
                        "#text": "https://lastfm-img2.akamaized.net/i/u/64s/1ab2389a384128536c3df2d79d736c43.png", 
                        "size": "medium"
                    }, 
                    {
                        "#text": "https://lastfm-img2.akamaized.net/i/u/174s/1ab2389a384128536c3df2d79d736c43.png", 
                        "size": "large"
                    }, 
                    {
                        "#text": "https://lastfm-img2.akamaized.net/i/u/300x300/1ab2389a384128536c3df2d79d736c43.png", 
                        "size": "extralarge"
                    }
                ], 
                "listeners": "16700", 
                "mbid": "", 
                "name": "Again", 
                "playcount": "87852", 
                "streamable": {
                    "#text": "0", 
                    "fulltrack": "0"
                }, 
                "url": "https://www.last.fm/music/Miley+Cyrus/_/Again"
            }, 
            {
                "artist": {
                    "mbid": "757ed661-fbad-4e45-b1cd-a6b09f06f54a", 
                    "name": "Yung Lean", 
                    "url": "https://www.last.fm/music/Yung+Lean"
                }, 
                "duration": "0", 
                "image": [
                    {
                        "#text": "https://lastfm-img2.akamaized.net/i/u/34s/da3e6b3b86cc52118267b4f8920a3167.png", 
                        "size": "small"
                    }, 
                    {
                        "#text": "https://lastfm-img2.akamaized.net/i/u/64s/da3e6b3b86cc52118267b4f8920a3167.png", 
                        "size": "medium"
                    }, 
                    {
                        "#text": "https://lastfm-img2.akamaized.net/i/u/174s/da3e6b3b86cc52118267b4f8920a3167.png", 
                        "size": "large"
                    }, 
                    {
                        "#text": "https://lastfm-img2.akamaized.net/i/u/300x300/da3e6b3b86cc52118267b4f8920a3167.png", 
                        "size": "extralarge"
                    }
                ], 
                "listeners": "7286", 
                "mbid": "", 
                "name": "Muddy Sea", 
                "playcount": "22359", 
                "streamable": {
                    "#text": "0", 
                    "fulltrack": "0"
                }, 
                "url": "https://www.last.fm/music/Yung+Lean/_/Muddy+Sea"
            }, 
            {
                "artist": {
                    "mbid": "bfcc6d75-a6a5-4bc6-8282-47aec8531818", 
                    "name": "Cher", 
                    "url": "https://www.last.fm/music/Cher"
                }, 
                "duration": "238", 
                "image": [
                    {
                        "#text": "https://lastfm-img2.akamaized.net/i/u/34s/4880fabfe1034196c1c70e55562cd8b8.png", 
                        "size": "small"
                    }, 
                    {
                        "#text": "https://lastfm-img2.akamaized.net/i/u/64s/4880fabfe1034196c1c70e55562cd8b8.png", 
                        "size": "medium"
                    }, 
                    {
                        "#text": "https://lastfm-img2.akamaized.net/i/u/174s/4880fabfe1034196c1c70e55562cd8b8.png", 
                        "size": "large"
                    }, 
                    {
                        "#text": "https://lastfm-img2.akamaized.net/i/u/300x300/4880fabfe1034196c1c70e55562cd8b8.png", 
                        "size": "extralarge"
                    }
                ], 
                "listeners": "410491", 
                "mbid": "32ca187e-ee25-4f18-b7d0-3b6713f24635", 
                "name": "Believe", 
                "playcount": "1921208", 
                "streamable": {
                    "#text": "0", 
                    "fulltrack": "0"
                }, 
                "url": "https://www.last.fm/music/Cher/_/Believe"
            }, 
            {
                "artist": {
                    "mbid": "c6be66af-28b4-4b87-a8ba-3f46ec6fe986", 
                    "name": "John Maus", 
                    "url": "https://www.last.fm/music/John+Maus"
                }, 
                "duration": "0", 
                "image": [
                    {
                        "#text": "https://lastfm-img2.akamaized.net/i/u/34s/d455383579fc41d283e4098400942dcb.png", 
                        "size": "small"
                    }, 
                    {
                        "#text": "https://lastfm-img2.akamaized.net/i/u/64s/d455383579fc41d283e4098400942dcb.png", 
                        "size": "medium"
                    }, 
                    {
                        "#text": "https://lastfm-img2.akamaized.net/i/u/174s/d455383579fc41d283e4098400942dcb.png", 
                        "size": "large"
                    }, 
                    {
                        "#text": "https://lastfm-img2.akamaized.net/i/u/300x300/d455383579fc41d283e4098400942dcb.png", 
                        "size": "extralarge"
                    }
                ], 
                "listeners": "8310", 
                "mbid": "", 
                "name": "Touchdown", 
                "playcount": "24020", 
                "streamable": {
                    "#text": "0", 
                    "fulltrack": "0"
                }, 
                "url": "https://www.last.fm/music/John+Maus/_/Touchdown"
            }, 
            {
                "artist": {
                    "mbid": "", 
                    "name": "Camila Cabello", 
                    "url": "https://www.last.fm/music/Camila+Cabello"
                }, 
                "duration": "0", 
                "image": [
                    {
                        "#text": "https://lastfm-img2.akamaized.net/i/u/34s/616bc82422cd590385137a9dbe1e68af.png", 
                        "size": "small"
                    }, 
                    {
                        "#text": "https://lastfm-img2.akamaized.net/i/u/64s/616bc82422cd590385137a9dbe1e68af.png", 
                        "size": "medium"
                    }, 
                    {
                        "#text": "https://lastfm-img2.akamaized.net/i/u/174s/616bc82422cd590385137a9dbe1e68af.png", 
                        "size": "large"
                    }, 
                    {
                        "#text": "https://lastfm-img2.akamaized.net/i/u/300x300/616bc82422cd590385137a9dbe1e68af.png", 
                        "size": "extralarge"
                    }
                ], 
                "listeners": "10895", 
                "mbid": "", 
                "name": "Havana (feat. Young Thug)", 
                "playcount": "164735", 
                "streamable": {
                    "#text": "0", 
                    "fulltrack": "0"
                }, 
                "url": "https://www.last.fm/music/Camila+Cabello/_/Havana+(feat.+Young+Thug)"
            }, 
            {
                "artist": {
                    "mbid": "a16371b9-7d36-497a-a9d4-42b0a0440c5e", 
                    "name": "Slowdive", 
                    "url": "https://www.last.fm/music/Slowdive"
                }, 
                "duration": "287", 
                "image": [
                    {
                        "#text": "https://lastfm-img2.akamaized.net/i/u/34s/6117351f898b4a90caed5444b8772bac.png", 
                        "size": "small"
                    }, 
                    {
                        "#text": "https://lastfm-img2.akamaized.net/i/u/64s/6117351f898b4a90caed5444b8772bac.png", 
                        "size": "medium"
                    }, 
                    {
                        "#text": "https://lastfm-img2.akamaized.net/i/u/174s/6117351f898b4a90caed5444b8772bac.png", 
                        "size": "large"
                    }, 
                    {
                        "#text": "https://lastfm-img2.akamaized.net/i/u/300x300/6117351f898b4a90caed5444b8772bac.png", 
                        "size": "extralarge"
                    }
                ], 
                "listeners": "201970", 
                "mbid": "ddfee9ee-aa94-48b7-b963-d0b69bef7c72", 
                "name": "When the Sun Hits", 
                "playcount": "1530560", 
                "streamable": {
                    "#text": "0", 
                    "fulltrack": "0"
                }, 
                "url": "https://www.last.fm/music/Slowdive/_/When+the+Sun+Hits"
            }, 
            {
                "artist": {
                    "mbid": "59a7fbcb-ff74-494d-abd0-9c82359040c9", 
                    "name": "Grizzly Bear", 
                    "url": "https://www.last.fm/music/Grizzly+Bear"
                }, 
                "duration": "0", 
                "image": [
                    {
                        "#text": "https://lastfm-img2.akamaized.net/i/u/34s/b78a441b90344a5aabb72fa089d22544.png", 
                        "size": "small"
                    }, 
                    {
                        "#text": "https://lastfm-img2.akamaized.net/i/u/64s/b78a441b90344a5aabb72fa089d22544.png", 
                        "size": "medium"
                    }, 
                    {
                        "#text": "https://lastfm-img2.akamaized.net/i/u/174s/b78a441b90344a5aabb72fa089d22544.png", 
                        "size": "large"
                    }, 
                    {
                        "#text": "https://lastfm-img2.akamaized.net/i/u/300x300/b78a441b90344a5aabb72fa089d22544.png", 
                        "size": "extralarge"
                    }
                ], 
                "listeners": "38745", 
                "mbid": "", 
                "name": "Four Cypresses", 
                "playcount": "132297", 
                "streamable": {
                    "#text": "0", 
                    "fulltrack": "0"
                }, 
                "url": "https://www.last.fm/music/Grizzly+Bear/_/Four+Cypresses"
            }, 
            {
                "artist": {
                    "mbid": "b49b81cc-d5b7-4bdd-aadb-385df8de69a6", 
                    "name": "Drake", 
                    "url": "https://www.last.fm/music/Drake"
                }, 
                "duration": "0", 
                "image": [
                    {
                        "#text": "https://lastfm-img2.akamaized.net/i/u/34s/93e7507e732722275768269b6c579a46.png", 
                        "size": "small"
                    }, 
                    {
                        "#text": "https://lastfm-img2.akamaized.net/i/u/64s/93e7507e732722275768269b6c579a46.png", 
                        "size": "medium"
                    }, 
                    {
                        "#text": "https://lastfm-img2.akamaized.net/i/u/174s/93e7507e732722275768269b6c579a46.png", 
                        "size": "large"
                    }, 
                    {
                        "#text": "https://lastfm-img2.akamaized.net/i/u/300x300/93e7507e732722275768269b6c579a46.png", 
                        "size": "extralarge"
                    }
                ], 
                "listeners": "64470", 
                "mbid": "", 
                "name": "Portland", 
                "playcount": "671176", 
                "streamable": {
                    "#text": "0", 
                    "fulltrack": "0"
                }, 
                "url": "https://www.last.fm/music/Drake/_/Portland"
            }, 
            {
                "artist": {
                    "mbid": "e520459c-dff4-491d-a6e4-c97be35e0044", 
                    "name": "Frank Ocean", 
                    "url": "https://www.last.fm/music/Frank+Ocean"
                }, 
                "duration": "0", 
                "image": [
                    {
                        "#text": "https://lastfm-img2.akamaized.net/i/u/34s/07b88e65882d07b34d0ba1aca46c4949.png", 
                        "size": "small"
                    }, 
                    {
                        "#text": "https://lastfm-img2.akamaized.net/i/u/64s/07b88e65882d07b34d0ba1aca46c4949.png", 
                        "size": "medium"
                    }, 
                    {
                        "#text": "https://lastfm-img2.akamaized.net/i/u/174s/07b88e65882d07b34d0ba1aca46c4949.png", 
                        "size": "large"
                    }, 
                    {
                        "#text": "https://lastfm-img2.akamaized.net/i/u/300x300/07b88e65882d07b34d0ba1aca46c4949.png", 
                        "size": "extralarge"
                    }
                ], 
                "listeners": "76338", 
                "mbid": "", 
                "name": "Godspeed", 
                "playcount": "453393", 
                "streamable": {
                    "#text": "0", 
                    "fulltrack": "0"
                }, 
                "url": "https://www.last.fm/music/Frank+Ocean/_/Godspeed"
            }, 
            {
                "artist": {
                    "mbid": "4fc58550-637f-496f-b6bc-3a62ba7f2f7e", 
                    "name": "AFI", 
                    "url": "https://www.last.fm/music/AFI"
                }, 
                "duration": "218", 
                "image": [
                    {
                        "#text": "https://lastfm-img2.akamaized.net/i/u/34s/80cd9530f9ef4c783873b1a39951ff98.png", 
                        "size": "small"
                    }, 
                    {
                        "#text": "https://lastfm-img2.akamaized.net/i/u/64s/80cd9530f9ef4c783873b1a39951ff98.png", 
                        "size": "medium"
                    }, 
                    {
                        "#text": "https://lastfm-img2.akamaized.net/i/u/174s/80cd9530f9ef4c783873b1a39951ff98.png", 
                        "size": "large"
                    }, 
                    {
                        "#text": "https://lastfm-img2.akamaized.net/i/u/300x300/80cd9530f9ef4c783873b1a39951ff98.png", 
                        "size": "extralarge"
                    }
                ], 
                "listeners": "515039", 
                "mbid": "320ab068-f72c-4b6b-9bff-c6efc34657d4", 
                "name": "Miss Murder", 
                "playcount": "3788194", 
                "streamable": {
                    "#text": "0", 
                    "fulltrack": "0"
                }, 
                "url": "https://www.last.fm/music/AFI/_/Miss+Murder"
            }, 
            {
                "artist": {
                    "mbid": "c1aa2ec9-53e7-4d90-8d36-bac75832e986", 
                    "name": "Stevie Wonder", 
                    "url": "https://www.last.fm/music/Stevie+Wonder"
                }, 
                "duration": "161", 
                "image": [
                    {
                        "#text": "https://lastfm-img2.akamaized.net/i/u/34s/cee3aeee325113a675c12ba386c2fb44.png", 
                        "size": "small"
                    }, 
                    {
                        "#text": "https://lastfm-img2.akamaized.net/i/u/64s/cee3aeee325113a675c12ba386c2fb44.png", 
                        "size": "medium"
                    }, 
                    {
                        "#text": "https://lastfm-img2.akamaized.net/i/u/174s/cee3aeee325113a675c12ba386c2fb44.png", 
                        "size": "large"
                    }, 
                    {
                        "#text": "https://lastfm-img2.akamaized.net/i/u/300x300/cee3aeee325113a675c12ba386c2fb44.png", 
                        "size": "extralarge"
                    }
                ], 
                "listeners": "245768", 
                "mbid": "9a4eda8c-a904-460e-8863-1bbdd2cc482c", 
                "name": "Signed, Sealed, Delivered (I'm Yours)", 
                "playcount": "877268", 
                "streamable": {
                    "#text": "0", 
                    "fulltrack": "0"
                }, 
                "url": "https://www.last.fm/music/Stevie+Wonder/_/Signed,+Sealed,+Delivered+(I%27m+Yours)"
            }, 
            {
                "artist": {
                    "mbid": "611700cf-27f0-4dc9-ae80-c513a767853e", 
                    "name": "Michael Bubl\u00e9", 
                    "url": "https://www.last.fm/music/Michael+Bubl%C3%A9"
                }, 
                "duration": "208", 
                "image": [
                    {
                        "#text": "https://lastfm-img2.akamaized.net/i/u/34s/a03401ae735b40e4c0545ae03fdc5490.png", 
                        "size": "small"
                    }, 
                    {
                        "#text": "https://lastfm-img2.akamaized.net/i/u/64s/a03401ae735b40e4c0545ae03fdc5490.png", 
                        "size": "medium"
                    }, 
                    {
                        "#text": "https://lastfm-img2.akamaized.net/i/u/174s/a03401ae735b40e4c0545ae03fdc5490.png", 
                        "size": "large"
                    }, 
                    {
                        "#text": "https://lastfm-img2.akamaized.net/i/u/300x300/a03401ae735b40e4c0545ae03fdc5490.png", 
                        "size": "extralarge"
                    }
                ], 
                "listeners": "244300", 
                "mbid": "71f5c990-0a83-4879-9e3b-fecf2fb2aa55", 
                "name": "It's Beginning to Look a Lot Like Christmas", 
                "playcount": "964631", 
                "streamable": {
                    "#text": "0", 
                    "fulltrack": "0"
                }, 
                "url": "https://www.last.fm/music/Michael+Bubl%C3%A9/_/It%27s+Beginning+to+Look+a+Lot+Like+Christmas"
            }, 
            {
                "artist": {
                    "mbid": "a8baaa41-50f1-4f63-979e-717c14979dfb", 
                    "name": "Beck", 
                    "url": "https://www.last.fm/music/Beck"
                }, 
                "duration": "0", 
                "image": [
                    {
                        "#text": "https://lastfm-img2.akamaized.net/i/u/34s/4678ffd278784bf381a24ef4b3493345.png", 
                        "size": "small"
                    }, 
                    {
                        "#text": "https://lastfm-img2.akamaized.net/i/u/64s/4678ffd278784bf381a24ef4b3493345.png", 
                        "size": "medium"
                    }, 
                    {
                        "#text": "https://lastfm-img2.akamaized.net/i/u/174s/4678ffd278784bf381a24ef4b3493345.png", 
                        "size": "large"
                    }, 
                    {
                        "#text": "https://lastfm-img2.akamaized.net/i/u/300x300/4678ffd278784bf381a24ef4b3493345.png", 
                        "size": "extralarge"
                    }
                ], 
                "listeners": "20023", 
                "mbid": "", 
                "name": "No Distraction", 
                "playcount": "55941", 
                "streamable": {
                    "#text": "0", 
                    "fulltrack": "0"
                }, 
                "url": "https://www.last.fm/music/Beck/_/No+Distraction"
            }
        ]
    }
}